kucoin/__init__.py
kucoin/ccxt/__init__.py
kucoin/ccxt/kucoin.py
kucoin/ccxt/abstract/kucoin.py
kucoin/ccxt/async_support/__init__.py
kucoin/ccxt/async_support/kucoin.py
kucoin/ccxt/async_support/base/__init__.py
kucoin/ccxt/async_support/base/exchange.py
kucoin/ccxt/async_support/base/throttler.py
kucoin/ccxt/async_support/base/ws/__init__.py
kucoin/ccxt/async_support/base/ws/cache.py
kucoin/ccxt/async_support/base/ws/client.py
kucoin/ccxt/async_support/base/ws/functions.py
kucoin/ccxt/async_support/base/ws/future.py
kucoin/ccxt/async_support/base/ws/order_book.py
kucoin/ccxt/async_support/base/ws/order_book_side.py
kucoin/ccxt/base/__init__.py
kucoin/ccxt/base/decimal_to_precision.py
kucoin/ccxt/base/errors.py
kucoin/ccxt/base/exchange.py
kucoin/ccxt/base/precise.py
kucoin/ccxt/base/types.py
kucoin/ccxt/pro/__init__.py
kucoin/ccxt/pro/kucoin.py
kucoin/ccxt/static_dependencies/README.md
kucoin/ccxt/static_dependencies/__init__.py
kucoin/ccxt/static_dependencies/bip/__init__.py
kucoin/ccxt/static_dependencies/bip/addr/P2PKH_addr.py
kucoin/ccxt/static_dependencies/bip/addr/__init__.py
kucoin/ccxt/static_dependencies/bip/addr/addr_dec_utils.py
kucoin/ccxt/static_dependencies/bip/addr/addr_key_validator.py
kucoin/ccxt/static_dependencies/bip/addr/iaddr_decoder.py
kucoin/ccxt/static_dependencies/bip/addr/iaddr_encoder.py
kucoin/ccxt/static_dependencies/bip/base58/__init__.py
kucoin/ccxt/static_dependencies/bip/base58/base58.py
kucoin/ccxt/static_dependencies/bip/base58/base58_ex.py
kucoin/ccxt/static_dependencies/bip/base58/base58_xmr.py
kucoin/ccxt/static_dependencies/bip/bech32/__init__.py
kucoin/ccxt/static_dependencies/bip/bech32/bch_bech32.py
kucoin/ccxt/static_dependencies/bip/bech32/bech32.py
kucoin/ccxt/static_dependencies/bip/bech32/bech32_base.py
kucoin/ccxt/static_dependencies/bip/bech32/bech32_ex.py
kucoin/ccxt/static_dependencies/bip/bech32/segwit_bech32.py
kucoin/ccxt/static_dependencies/bip/bip32/__init__.py
kucoin_api-0.0.124.dist-info/METADATA
kucoin_api-0.0.124.dist-info/WHEEL
kucoin_api-0.0.124.dist-info/RECORD
